{
	"format_version": "1.12.0",
	"minecraft:geometry": [
		{
			"description": {
				"identifier": "geometry.unknown",
				"texture_width": 64,
				"texture_height": 64,
				"visible_bounds_width": 2,
				"visible_bounds_height": 2.5,
				"visible_bounds_offset": [0, 0.75, 0]
			},
			"bones": [
				{
					"name": "Outside",
					"pivot": [0, 0, 0],
					"cubes": [
						{"origin": [-8, 12, -6], "size": [2, 2, 2], "uv": [32, 24]},
						{"origin": [-6, 2, 6], "size": [2, 2, 2], "uv": [32, 60]},
						{"origin": [-8, 0, 6], "size": [2, 2, 2], "uv": [20, 60]},
						{"origin": [-4, 0, 6], "size": [2, 2, 2], "uv": [8, 60]},
						{"origin": [-2, 2, 6], "size": [2, 2, 2], "uv": [50, 58]},
						{"origin": [4, 0, 6], "size": [2, 2, 2], "uv": [38, 58]},
						{"origin": [0, 0, 6], "size": [2, 2, 2], "uv": [26, 58]},
						{"origin": [6, 2, 6], "size": [2, 2, 2], "uv": [14, 58]},
						{"origin": [2, 2, 6], "size": [2, 2, 2], "uv": [2, 58]},
						{"origin": [6, 0, 4], "size": [2, 2, 2], "uv": [56, 56]},
						{"origin": [6, 0, 0], "size": [2, 2, 2], "uv": [56, 52]},
						{"origin": [6, 2, 2], "size": [2, 2, 2], "uv": [56, 48]},
						{"origin": [6, 0, -4], "size": [2, 2, 2], "uv": [56, 44]},
						{"origin": [6, 2, -2], "size": [2, 2, 2], "uv": [44, 56]},
						{"origin": [6, 0, -8], "size": [2, 2, 2], "uv": [56, 40]},
						{"origin": [6, 2, -6], "size": [2, 2, 2], "uv": [56, 36]},
						{"origin": [2, 0, -8], "size": [2, 2, 2], "uv": [56, 32]},
						{"origin": [4, 2, -8], "size": [2, 2, 2], "uv": [32, 56]},
						{"origin": [0, 2, -8], "size": [2, 2, 2], "uv": [56, 28]},
						{"origin": [-2, 0, -8], "size": [2, 2, 2], "uv": [56, 24]},
						{"origin": [-4, 2, -8], "size": [2, 2, 2], "uv": [56, 20]},
						{"origin": [-6, 0, -8], "size": [2, 2, 2], "uv": [20, 56]},
						{"origin": [-8, 2, 4], "size": [2, 2, 2], "uv": [56, 16]},
						{"origin": [-8, 2, 0], "size": [2, 2, 2], "uv": [56, 12]},
						{"origin": [-8, 0, 2], "size": [2, 2, 2], "uv": [56, 8]},
						{"origin": [-8, 2, -4], "size": [2, 2, 2], "uv": [8, 56]},
						{"origin": [-8, 0, -2], "size": [2, 2, 2], "uv": [56, 4]},
						{"origin": [-8, 2, -8], "size": [2, 2, 2], "uv": [50, 54]},
						{"origin": [-8, 0, -6], "size": [2, 2, 2], "uv": [38, 54]},
						{"origin": [-6, 0, -4], "size": [2, 2, 2], "uv": [26, 54]},
						{"origin": [-6, 0, 0], "size": [2, 2, 2], "uv": [14, 54]},
						{"origin": [-6, 0, 4], "size": [2, 2, 2], "uv": [2, 54]},
						{"origin": [-4, 0, -6], "size": [2, 2, 2], "uv": [44, 52]},
						{"origin": [-4, 0, -2], "size": [2, 2, 2], "uv": [32, 52]},
						{"origin": [-4, 0, 2], "size": [2, 2, 2], "uv": [20, 52]},
						{"origin": [-2, 0, -4], "size": [2, 2, 2], "uv": [8, 52]},
						{"origin": [-2, 0, 0], "size": [2, 2, 2], "uv": [50, 50]},
						{"origin": [-2, 0, 4], "size": [2, 2, 2], "uv": [50, 46]},
						{"origin": [0, 0, -6], "size": [2, 2, 2], "uv": [50, 42]},
						{"origin": [0, 0, -2], "size": [2, 2, 2], "uv": [50, 38]},
						{"origin": [0, 0, 2], "size": [2, 2, 2], "uv": [38, 50]},
						{"origin": [2, 0, 4], "size": [2, 2, 2], "uv": [50, 34]},
						{"origin": [2, 0, 0], "size": [2, 2, 2], "uv": [50, 30]},
						{"origin": [2, 0, -4], "size": [2, 2, 2], "uv": [50, 26]},
						{"origin": [4, 0, 2], "size": [2, 2, 2], "uv": [26, 50]},
						{"origin": [4, 0, -6], "size": [2, 2, 2], "uv": [50, 22]},
						{"origin": [4, 0, -2], "size": [2, 2, 2], "uv": [50, 18]},
						{"origin": [-8, 4, -6], "size": [2, 2, 2], "uv": [50, 14]},
						{"origin": [-8, 6, -8], "size": [2, 2, 2], "uv": [14, 50]},
						{"origin": [-8, 4, -2], "size": [2, 2, 2], "uv": [50, 10]},
						{"origin": [-8, 6, -4], "size": [2, 2, 2], "uv": [50, 6]},
						{"origin": [-8, 4, 2], "size": [2, 2, 2], "uv": [50, 2]},
						{"origin": [-8, 6, 0], "size": [2, 2, 2], "uv": [2, 50]},
						{"origin": [-8, 6, 4], "size": [2, 2, 2], "uv": [44, 48]},
						{"origin": [-6, 4, -8], "size": [2, 2, 2], "uv": [32, 48]},
						{"origin": [-4, 6, -8], "size": [2, 2, 2], "uv": [20, 48]},
						{"origin": [-2, 4, -8], "size": [2, 2, 2], "uv": [8, 48]},
						{"origin": [0, 6, -8], "size": [2, 2, 2], "uv": [38, 46]},
						{"origin": [4, 6, -8], "size": [2, 2, 2], "uv": [26, 46]},
						{"origin": [2, 4, -8], "size": [2, 2, 2], "uv": [14, 46]},
						{"origin": [6, 6, -6], "size": [2, 2, 2], "uv": [2, 46]},
						{"origin": [6, 4, -8], "size": [2, 2, 2], "uv": [44, 44]},
						{"origin": [6, 6, -2], "size": [2, 2, 2], "uv": [44, 40]},
						{"origin": [6, 4, -4], "size": [2, 2, 2], "uv": [44, 36]},
						{"origin": [6, 4, 0], "size": [2, 2, 2], "uv": [44, 32]},
						{"origin": [6, 4, 4], "size": [2, 2, 2], "uv": [32, 44]},
						{"origin": [2, 6, 6], "size": [2, 2, 2], "uv": [44, 28]},
						{"origin": [6, 6, 6], "size": [2, 2, 2], "uv": [44, 24]},
						{"origin": [0, 4, 6], "size": [2, 2, 2], "uv": [44, 20]},
						{"origin": [4, 4, 6], "size": [2, 2, 2], "uv": [20, 44]},
						{"origin": [-2, 6, 6], "size": [2, 2, 2], "uv": [44, 16]},
						{"origin": [-4, 4, 6], "size": [2, 2, 2], "uv": [44, 12]},
						{"origin": [-8, 4, 6], "size": [2, 2, 2], "uv": [44, 8]},
						{"origin": [-6, 6, 6], "size": [2, 2, 2], "uv": [8, 44]},
						{"origin": [6, 6, 2], "size": [2, 2, 2], "uv": [44, 4]},
						{"origin": [-8, 8, -6], "size": [2, 2, 2], "uv": [38, 42]},
						{"origin": [-8, 10, -8], "size": [2, 2, 2], "uv": [26, 42]},
						{"origin": [-8, 8, -2], "size": [2, 2, 2], "uv": [14, 42]},
						{"origin": [-8, 10, -4], "size": [2, 2, 2], "uv": [2, 42]},
						{"origin": [-8, 8, 2], "size": [2, 2, 2], "uv": [32, 40]},
						{"origin": [-8, 10, 0], "size": [2, 2, 2], "uv": [20, 40]},
						{"origin": [-8, 10, 4], "size": [2, 2, 2], "uv": [8, 40]},
						{"origin": [-6, 8, -8], "size": [2, 2, 2], "uv": [38, 38]},
						{"origin": [-4, 10, -8], "size": [2, 2, 2], "uv": [38, 34]},
						{"origin": [-2, 8, -8], "size": [2, 2, 2], "uv": [38, 30]},
						{"origin": [0, 10, -8], "size": [2, 2, 2], "uv": [38, 26]},
						{"origin": [4, 10, -8], "size": [2, 2, 2], "uv": [26, 38]},
						{"origin": [2, 8, -8], "size": [2, 2, 2], "uv": [38, 22]},
						{"origin": [6, 10, -6], "size": [2, 2, 2], "uv": [38, 18]},
						{"origin": [6, 8, -8], "size": [2, 2, 2], "uv": [38, 14]},
						{"origin": [6, 10, -2], "size": [2, 2, 2], "uv": [14, 38]},
						{"origin": [6, 8, -4], "size": [2, 2, 2], "uv": [38, 10]},
						{"origin": [6, 8, 0], "size": [2, 2, 2], "uv": [38, 6]},
						{"origin": [6, 8, 4], "size": [2, 2, 2], "uv": [38, 2]},
						{"origin": [2, 10, 6], "size": [2, 2, 2], "uv": [2, 38]},
						{"origin": [6, 10, 6], "size": [2, 2, 2], "uv": [32, 36]},
						{"origin": [0, 8, 6], "size": [2, 2, 2], "uv": [20, 36]},
						{"origin": [4, 8, 6], "size": [2, 2, 2], "uv": [8, 36]},
						{"origin": [-2, 10, 6], "size": [2, 2, 2], "uv": [26, 34]},
						{"origin": [-4, 8, 6], "size": [2, 2, 2], "uv": [14, 34]},
						{"origin": [-8, 8, 6], "size": [2, 2, 2], "uv": [2, 34]},
						{"origin": [-6, 10, 6], "size": [2, 2, 2], "uv": [32, 32]},
						{"origin": [6, 10, 2], "size": [2, 2, 2], "uv": [32, 28]},
						{"origin": [-8, 14, -8], "size": [2, 2, 2], "uv": [32, 20]},
						{"origin": [-8, 12, -2], "size": [2, 2, 2], "uv": [20, 32]},
						{"origin": [-8, 14, -4], "size": [2, 2, 2], "uv": [32, 16]},
						{"origin": [-8, 12, 2], "size": [2, 2, 2], "uv": [32, 12]},
						{"origin": [-8, 14, 0], "size": [2, 2, 2], "uv": [32, 8]},
						{"origin": [-8, 14, 4], "size": [2, 2, 2], "uv": [8, 32]},
						{"origin": [-6, 12, -8], "size": [2, 2, 2], "uv": [32, 4]},
						{"origin": [-4, 14, -8], "size": [2, 2, 2], "uv": [26, 30]},
						{"origin": [-2, 12, -8], "size": [2, 2, 2], "uv": [14, 30]},
						{"origin": [0, 14, -8], "size": [2, 2, 2], "uv": [2, 30]},
						{"origin": [4, 14, -8], "size": [2, 2, 2], "uv": [20, 28]},
						{"origin": [2, 12, -8], "size": [2, 2, 2], "uv": [8, 28]},
						{"origin": [6, 14, -6], "size": [2, 2, 2], "uv": [26, 26]},
						{"origin": [6, 12, -8], "size": [2, 2, 2], "uv": [26, 22]},
						{"origin": [6, 14, -2], "size": [2, 2, 2], "uv": [26, 18]},
						{"origin": [6, 12, -4], "size": [2, 2, 2], "uv": [32, 37]},
						{"origin": [6, 12, 0], "size": [2, 2, 2], "uv": [14, 26]},
						{"origin": [6, 12, 4], "size": [2, 2, 2], "uv": [32, 33]},
						{"origin": [2, 14, 6], "size": [2, 2, 2], "uv": [32, 29]},
						{"origin": [6, 14, 6], "size": [2, 2, 2], "uv": [32, 25]},
						{"origin": [0, 12, 6], "size": [2, 2, 2], "uv": [2, 26]},
						{"origin": [4, 12, 6], "size": [2, 2, 2], "uv": [20, 24]},
						{"origin": [-2, 14, 6], "size": [2, 2, 2], "uv": [8, 24]},
						{"origin": [-4, 12, 6], "size": [2, 2, 2], "uv": [14, 22]},
						{"origin": [-8, 12, 6], "size": [2, 2, 2], "uv": [2, 22]},
						{"origin": [-6, 14, 6], "size": [2, 2, 2], "uv": [20, 20]},
						{"origin": [6, 14, 2], "size": [2, 2, 2], "uv": [20, 16]},
						{"origin": [-6, 14, 4], "size": [2, 2, 2], "pivot": [0, 0, 0], "rotation": [0, 90, 0], "uv": [26, 35]},
						{"origin": [-2, 14, 4], "size": [2, 2, 2], "pivot": [0, 0, 0], "rotation": [0, 90, 0], "uv": [26, 31]},
						{"origin": [-6, 14, 0], "size": [2, 2, 2], "pivot": [0, 0, 0], "rotation": [0, 90, 0], "uv": [8, 20]},
						{"origin": [-4, 14, -2], "size": [2, 2, 2], "pivot": [0, 0, 0], "rotation": [0, 90, 0], "uv": [26, 27]},
						{"origin": [-4, 14, 2], "size": [2, 2, 2], "pivot": [0, 0, 0], "rotation": [0, 90, 0], "uv": [14, 18]},
						{"origin": [-2, 14, 0], "size": [2, 2, 2], "pivot": [0, 0, 0], "rotation": [0, 90, 0], "uv": [2, 18]},
						{"origin": [0, 14, 2], "size": [2, 2, 2], "pivot": [0, 0, 0], "rotation": [0, 90, 0], "uv": [8, 16]},
						{"origin": [2, 14, 4], "size": [2, 2, 2], "pivot": [0, 0, 0], "rotation": [0, 90, 0], "uv": [20, 37]},
						{"origin": [4, 14, 2], "size": [2, 2, 2], "pivot": [0, 0, 0], "rotation": [0, 90, 0], "uv": [20, 33]},
						{"origin": [2, 14, 0], "size": [2, 2, 2], "pivot": [0, 0, 0], "rotation": [0, 90, 0], "uv": [20, 29]},
						{"origin": [4, 14, -2], "size": [2, 2, 2], "pivot": [0, 0, 0], "rotation": [0, 90, 0], "uv": [20, 25]},
						{"origin": [0, 14, -2], "size": [2, 2, 2], "pivot": [0, 0, 0], "rotation": [0, 90, 0], "uv": [8, 37]},
						{"origin": [2, 14, -4], "size": [2, 2, 2], "pivot": [0, 0, 0], "rotation": [0, 90, 0], "uv": [14, 35]},
						{"origin": [0, 14, -6], "size": [2, 2, 2], "pivot": [0, 0, 0], "rotation": [0, 90, 0], "uv": [8, 33]},
						{"origin": [-2, 14, -4], "size": [2, 2, 2], "pivot": [0, 0, 0], "rotation": [0, 90, 0], "uv": [14, 31]},
						{"origin": [-4, 14, -6], "size": [2, 2, 2], "pivot": [0, 0, 0], "rotation": [0, 90, 0], "uv": [14, 27]},
						{"origin": [-6, 14, -4], "size": [2, 2, 2], "pivot": [0, 0, 0], "rotation": [0, 90, 0], "uv": [8, 29]},
						{"origin": [4, 14, -6], "size": [2, 2, 2], "pivot": [0, 0, 0], "rotation": [0, 90, 0], "uv": [8, 25]}
					]
				},
				{
					"name": "Inside",
					"pivot": [0, 8, 0],
					"cubes": [
						{"origin": [-4, 4, -4], "size": [8, 8, 8], "uv": [0, 0]}
					]
				}
			]
		}
	]
}